{
    "asset": {
        "format": "JPG",
        "id": "05405f21b61fa00016705538da3570bf",
        "name": "DJI_0144.JPG",
        "path": "file:/home/gonzalo/Escritorio/CONICET/MDPI/YOLO-MDPI/TrainYourOwnYOLO/Data/Source_Images/Training_Images/DJI_0144.JPG",
        "size": {
            "width": 4864,
            "height": 3648
        },
        "state": 2,
        "type": 1
    },
    "regions": [
        {
            "id": "3AcExVEo5",
            "type": "RECTANGLE",
            "tags": [
                "yacaré"
            ],
            "boundingBox": {
                "height": 230.80492091388402,
                "width": 134.57707509881422,
                "left": 934.6297760210804,
                "top": 1263.0158172231986
            },
            "points": [
                {
                    "x": 934.6297760210804,
                    "y": 1263.0158172231986
                },
                {
                    "x": 1069.2068511198945,
                    "y": 1263.0158172231986
                },
                {
                    "x": 1069.2068511198945,
                    "y": 1493.8207381370826
                },
                {
                    "x": 934.6297760210804,
                    "y": 1493.8207381370826
                }
            ]
        },
        {
            "id": "ugnAYu1uv",
            "type": "RECTANGLE",
            "tags": [
                "yacaré"
            ],
            "boundingBox": {
                "height": 160.2811950790861,
                "width": 128.16864295125163,
                "left": 242.51910408432147,
                "top": 359.02987697715287
            },
            "points": [
                {
                    "x": 242.51910408432147,
                    "y": 359.02987697715287
                },
                {
                    "x": 370.6877470355731,
                    "y": 359.02987697715287
                },
                {
                    "x": 370.6877470355731,
                    "y": 519.311072056239
                },
                {
                    "x": 242.51910408432147,
                    "y": 519.311072056239
                }
            ]
        },
        {
            "id": "TfHCwPi96",
            "type": "RECTANGLE",
            "tags": [
                "yacaré"
            ],
            "boundingBox": {
                "height": 179.51493848857643,
                "width": 192.25296442687747,
                "left": 31.040843214756258,
                "top": 1224.548330404218
            },
            "points": [
                {
                    "x": 31.040843214756258,
                    "y": 1224.548330404218
                },
                {
                    "x": 223.29380764163372,
                    "y": 1224.548330404218
                },
                {
                    "x": 223.29380764163372,
                    "y": 1404.0632688927944
                },
                {
                    "x": 31.040843214756258,
                    "y": 1404.0632688927944
                }
            ]
        },
        {
            "id": "oYRQReHjQ",
            "type": "RECTANGLE",
            "tags": [
                "yacaré"
            ],
            "boundingBox": {
                "height": 83.34622144112478,
                "width": 89.71805006587616,
                "left": 229.7022397891963,
                "top": 3308.2038664323372
            },
            "points": [
                {
                    "x": 229.7022397891963,
                    "y": 3308.2038664323372
                },
                {
                    "x": 319.42028985507244,
                    "y": 3308.2038664323372
                },
                {
                    "x": 319.42028985507244,
                    "y": 3391.550087873462
                },
                {
                    "x": 229.7022397891963,
                    "y": 3391.550087873462
                }
            ]
        }
    ],
    "version": "2.2.0"
}