{
    "asset": {
        "format": "JPG",
        "id": "d5bbe32a840a2455a91f5fe719cdc792",
        "name": "DJI_0409.JPG",
        "path": "file:/home/gonzalo/Escritorio/CONICET/MDPI/YOLO-MDPI/TrainYourOwnYOLO/Data/Source_Images/Training_Images/DJI_0409.JPG",
        "size": {
            "width": 4864,
            "height": 3648
        },
        "state": 2,
        "type": 1
    },
    "regions": [
        {
            "id": "EiKi2Sn_3",
            "type": "RECTANGLE",
            "tags": [
                "tortuga"
            ],
            "boundingBox": {
                "height": 64.11247803163445,
                "width": 57.675889328063235,
                "left": 2709.7654808959155,
                "top": 1455.353251318102
            },
            "points": [
                {
                    "x": 2709.7654808959155,
                    "y": 1455.353251318102
                },
                {
                    "x": 2767.441370223979,
                    "y": 1455.353251318102
                },
                {
                    "x": 2767.441370223979,
                    "y": 1519.4657293497364
                },
                {
                    "x": 2709.7654808959155,
                    "y": 1519.4657293497364
                }
            ]
        },
        {
            "id": "SFZNvr28B",
            "type": "RECTANGLE",
            "tags": [
                "yacaré"
            ],
            "boundingBox": {
                "height": 166.69244288224957,
                "width": 140.9855072463768,
                "left": 2748.216073781291,
                "top": 1378.4182776801406
            },
            "points": [
                {
                    "x": 2748.216073781291,
                    "y": 1378.4182776801406
                },
                {
                    "x": 2889.201581027668,
                    "y": 1378.4182776801406
                },
                {
                    "x": 2889.201581027668,
                    "y": 1545.11072056239
                },
                {
                    "x": 2748.216073781291,
                    "y": 1545.11072056239
                }
            ]
        }
    ],
    "version": "2.2.0"
}