{
    "asset": {
        "format": "JPG",
        "id": "e21751589ebaeb8cb897d71e5b0bdbee",
        "name": "DJI_0123.JPG",
        "path": "file:/home/gonzalo/Escritorio/CONICET/MDPI/YOLO-MDPI/TrainYourOwnYOLO/Data/Source_Images/Training_Images/DJI_0123.JPG",
        "size": {
            "width": 4864,
            "height": 3648
        },
        "state": 2,
        "type": 1
    },
    "regions": [
        {
            "id": "D9qUm33gd",
            "type": "RECTANGLE",
            "tags": [
                "yacaré"
            ],
            "boundingBox": {
                "height": 89.75746924428822,
                "width": 83.30961791831356,
                "left": 1524.2055335968378,
                "top": 2295.2267135325133
            },
            "points": [
                {
                    "x": 1524.2055335968378,
                    "y": 2295.2267135325133
                },
                {
                    "x": 1607.5151515151515,
                    "y": 2295.2267135325133
                },
                {
                    "x": 1607.5151515151515,
                    "y": 2384.9841827768014
                },
                {
                    "x": 1524.2055335968378,
                    "y": 2384.9841827768014
                }
            ]
        },
        {
            "id": "ewLbm7BOi",
            "type": "RECTANGLE",
            "tags": [
                "yacaré"
            ],
            "boundingBox": {
                "height": 83.34622144112478,
                "width": 57.675889328063235,
                "left": 2530.329380764163,
                "top": 2218.291739894552
            },
            "points": [
                {
                    "x": 2530.329380764163,
                    "y": 2218.291739894552
                },
                {
                    "x": 2588.0052700922265,
                    "y": 2218.291739894552
                },
                {
                    "x": 2588.0052700922265,
                    "y": 2301.6379613356767
                },
                {
                    "x": 2530.329380764163,
                    "y": 2301.6379613356767
                }
            ]
        }
    ],
    "version": "2.2.0"
}